<Article xmlns:xsi="http://www.w3.org/2001/XMLSchema-instance" xsi:noNamespaceSchemaLocation="Article.xsd">
	<Meta>
		<Attribution Url="http://www.mayoclinic.com">
			Content provided by MayoClinic.com
		</Attribution>
		<ContentType>
			Article
		</ContentType>
		<CopyrightOwner DocID="MayoCopyright">
			33DF435C-58F5-47FE-B83E25C1B9EA9A15
		</CopyrightOwner>
		<DocID>
			FL00003
		</DocID>
		<OriginalURL>
			http://www.mayoclinic.com/health/child-safety/FL00003
		</OriginalURL>
		<UpdateDate>
			2011-02-12
		</UpdateDate>
		<PublicationDate>
			2000-09-15
		</PublicationDate>
		<ControlWords>
			<Category MCVID="1000" Title="Age">
				<Keyword MCVID="1118" Title="Child">
					<Keyword MCVID="1121" Title="03 to 5 years preschool" />
				</Keyword>
			</Category>
			<Category MCVID="1000" Title="Age">
				<Keyword MCVID="1118" Title="Child">
					<Keyword MCVID="1122" Title="06 to 12 years elementary/preteen" />
				</Keyword>
			</Category>
			<Category MCVID="1000" Title="Age">
				<Keyword MCVID="1118" Title="Child">
					<Keyword MCVID="1123" Title="13 to 18 years teen" />
				</Keyword>
			</Category>
			<Category MCVID="1463" Title="Life stage">
				<Keyword MCVID="1533" Title="Children">
					<Keyword MCVID="3747" Title="Infants and toddlers">
						<Keyword MCVID="3751" Title="Toddler health" />
					</Keyword>
				</Keyword>
			</Category>
		</ControlWords>
		<ObjectID>
			7BE6C7FC-693C-4499-8372760D4E82717F
		</ObjectID>
		<MayoVersion>
			4
		</MayoVersion>
		<MetaKeywords>
			<MetaKeyword>
				child safety
			</MetaKeyword>
			<MetaKeyword>
				prevent falls
			</MetaKeyword>
			<MetaKeyword>
				fall safety for kids
			</MetaKeyword>
		</MetaKeywords>
		<HasFlash>
			0
		</HasFlash>
		<Source />
		<TermsOfUse DocID="AM00021" />
	</Meta>
	<Body>
		<Section>
			<SectionHead />
			<HTML>
				&lt;p&gt;
Every parent knows how hard it is to protect a child from injuries related to falling. When a baby first learns to walk, preventing falls requires constant supervision. Later, a toddler who&apos;s not as likely to fall while walking may tumble during a covert ascent to the cookie jar &amp;mdash; and an older child may miscalculate the physics involved in rocketing up a flight of hardwood stairs in socks. Still, there&apos;s plenty you can do to promote fall safety for kids. 
&lt;/p&gt;
			</HTML>
		</Section>
		<Section>
			<SectionHead>
				Fall safety for kids at home
			</SectionHead>
			<HTML>
				&lt;p&gt;
At home, fall safety for kids hinges on basic precautions. Follow these simple tips: 
&lt;/p&gt;
&lt;ul&gt;
	&lt;li&gt;&lt;strong&gt;Beware of heights.&lt;/strong&gt; Never leave a baby alone on a bed, changing table or piece of furniture. Use the safety strap on highchairs and other infant seats. Don&apos;t allow a young child to play alone on a fire escape, high porch or balcony. Safety netting also may help prevent falls. &lt;/li&gt;
	&lt;li&gt;&lt;strong&gt;Keep stairs safe.&lt;/strong&gt; Make sure stairs have handrails on both sides that go from the top step to the bottom step. Keep stairs clear of clutter and well lit.&lt;/li&gt;
	&lt;li&gt;&lt;strong&gt;Install safety gates.&lt;/strong&gt; Block a toddler&apos;s access to stairs with safety gates. If you&apos;re putting a safety gate at the top of a staircase, attach it to the wall.&lt;/li&gt;
	&lt;li&gt;&lt;strong&gt;Keep windows locked and screens in place.&lt;/strong&gt; A young child may squeeze through a window opened as little as 5 inches (12.7 centimeters). Although all windows that open should have guards or screens, screens aren&apos;t strong enough to keep a child inside. Discourage play near windows and patio doors, which could lead to a fall through glass. Don&apos;t store or display anything a child could climb near a window.&lt;/li&gt;
	&lt;li&gt;&lt;strong&gt;Prevent access to extension cords and ladders.&lt;/strong&gt; It&apos;s easy to trip on extension cords. Store ladders on their sides in a shed or garage.&lt;/li&gt;
	&lt;li&gt;&lt;strong&gt;Address slippery or uneven surfaces.&lt;/strong&gt; Use a rubber pad in the bathtub to help prevent slipping and clean kitchen spills quickly. Use foam carpet padding, double-sided tape or a rubber pad under area rugs to keep them from sliding. Fix chipped or broken steps and walkways as soon as possible.&lt;/li&gt;
	&lt;li&gt;&lt;strong&gt;Avoid baby walkers.&lt;/strong&gt; A young child may trip over a baby walker, fall out of the walker or fall down the stairs while using a walker.&lt;/li&gt;
	&lt;li&gt;&lt;strong&gt;Use night lights. &lt;/strong&gt;Consider using them in your child&apos;s bedroom, the bathroom and hallways to prevent falls at night. &lt;/li&gt;
&lt;/ul&gt;
&lt;p&gt;
Despite your best attempts to promote child safety at home, falls are still possible. To reduce the risk of injury, cover sharp furniture and fireplace corners with corner or edge bumpers. 
&lt;/p&gt;
			</HTML>
		</Section>
		<Section>
			<SectionHead>
				Fall safety for kids on the go
			</SectionHead>
			<HTML>
				&lt;p&gt;
When you&apos;re out and about, continue to keep fall safety for kids in mind: 
&lt;/p&gt;
&lt;ul&gt;
	&lt;li&gt;&lt;strong&gt;Fasten safety belts.&lt;/strong&gt; Always strap children into car seats, strollers and shopping cart seats. Never leave your child unattended in a shopping cart or allow him or her to stand up or ride in the basket of the cart &amp;mdash; which could tip over. &lt;/li&gt;
	&lt;li&gt;&lt;strong&gt;Examine playgrounds.&lt;/strong&gt; Under play equipment, look for surfaces made of wood chips, mulch or shredded rubber. Try to remove tripping hazards, such as rocks, and steer your child to age-appropriate activities. &lt;/li&gt;
	&lt;li&gt;&lt;strong&gt;Beware of escalators.&lt;/strong&gt; Avoid bringing strollers onto escalators. Always carry your child or hold his or her hand as you ride, and watch for dangling clothing. &lt;/li&gt;
	&lt;li&gt;&lt;strong&gt;Watch for slippery surfaces.&lt;/strong&gt; Encourage your child to approach wet, dark and paved areas with caution in cold temperatures. Make sure your child wears shoes or boots with traction in bad weather. A heavy or bulky coat can provide cushioning in the event of a fall.&lt;/li&gt;
&lt;/ul&gt;
&lt;p&gt;
Keeping your child safe from falls takes more than luck. Follow these precautions and you&apos;ll go a long way toward preventing injuries. 
&lt;/p&gt;
			</HTML>
		</Section>
	</Body>
	<Title>
		Fall safety for kids: How to prevent falls
	</Title>
	<Abstract>
		Fall safety for kids &amp;mdash; Prevent falls by taking these simple precautions.
	</Abstract>
	<BenefitSummary>
		Curious about fall safety for kids? Taking some simple precautions at home and on the go can help reduce your child&apos;s risk of falling.
	</BenefitSummary>
	<RelatedLinksBox>
		<LinkItem ContentType="Answer" DocID="AN02174" LinkType="Internal" ObjectID="ED8A9C78-E24E-B715-A576239249123DBB" Title="Head lice prevention: What works, what doesn&apos;t?" Url="http://www.mayoclinic.com/health/head-lice-prevention/AN02174" />
		<LinkItem ContentType="Article" DocID="MY00522" LinkType="Internal" ObjectID="DB545634-D392-85C6-1E6A99117A2A88A5" Title="Children and TV: Limiting your child&apos;s screen time" Url="http://www.mayoclinic.com/health/children-and-tv/MY00522" />
		<LinkItem ContentType="Article" DocID="CC00083" LinkType="Internal" ObjectID="D73C9C67-E7FF-0DBD-1906123BF1D6371C" Title="Cold medicines for kids: What&apos;s the risk?" Url="http://www.mayoclinic.com/health/cold-medicines/CC00083" />
		<LinkItem ContentType="Article" DocID="HO00002" LinkType="Internal" ObjectID="99E818C7-6EDD-4A1B-8170BAAECEC4B2E8" Title="Acetaminophen and children: Why dose matters" Url="http://www.mayoclinic.com/health/acetaminophen/HO00002" />
		<LinkItem ContentType="Article" DocID="MY01940" LinkType="Internal" ObjectID="14DFFCC1-A3D2-56CB-D63B21FDDC6EA09C" Title="New sibling: Preparing your older child" Url="http://www.mayoclinic.com/health/new-sibling/MY01940" />
		<LinkItem ContentType="Article" DocID="HQ00547" LinkType="Internal" ObjectID="0F87394A-8132-4238-8419DA040B33B181" Title="Sex education: Talking to toddlers and preschoolers about sex" Url="http://www.mayoclinic.com/health/sex-education/HQ00547" />
		<LinkItem ContentType="Table" DocID="MY00136" LinkType="Internal" ObjectID="D9F25138-E7FF-0DBD-1FA64BEACF230E0C" Title="Child development chart: Preschool milestones" Url="http://www.mayoclinic.com/health/child-development/MY00136" />
		<LinkItem ContentType="Disease" DocID="DS00892" LinkType="Internal" ObjectID="C42BC11D-E7FF-0DBD-1B7A0231D1304090" Title="Ringworm (scalp)" Url="http://www.mayoclinic.com/health/ringworm/DS00892" />
		<LinkItem ContentType="Article" DocID="HQ01622" LinkType="Internal" ObjectID="D63FCB69-BC7C-4952-B5F3BAAAD79A91DA" Title="Temper tantrums in toddlers: How to keep the peace" Url="http://www.mayoclinic.com/health/tantrum/HQ01622" />
		<LinkItem ContentType="Article" DocID="CC00060" LinkType="Internal" ObjectID="47E34F63-FB6F-471B-A788275BDC8C7911" Title="Potty training: How to get the job done" Url="http://www.mayoclinic.com/health/potty-training/CC00060" />
		<LinkItem ContentType="Article" DocID="CC00003" LinkType="Internal" ObjectID="375B9F20-3199-4C74-8E40CA18D7DE15D3" Title="Kids&apos; swimming: Keep health risks at bay" Url="http://www.mayoclinic.com/health/childrens-health/CC00003" />
		<LinkItem ContentType="Article" DocID="CC00045" LinkType="Internal" ObjectID="2AAF524A-BDFB-4E02-80DA2FFA866089F0" Title="Water safety: Protect your child from drowning" Url="http://www.mayoclinic.com/health/child-safety/CC00045" />
		<LinkItem ContentType="Article" DocID="CC00044" LinkType="Internal" ObjectID="0B1AC7EB-5E8E-4BB3-ACCED37422A83BF7" Title="Burn safety: Protect your child from burns" Url="http://www.mayoclinic.com/health/child-safety/CC00044" />
	</RelatedLinksBox>
</Article>
